spa/__init__.py
spa_json_py-0.0.1.dist-info/LICENSE
spa_json_py-0.0.1.dist-info/METADATA
spa_json_py-0.0.1.dist-info/WHEEL
spa_json_py-0.0.1.dist-info/RECORD
