Metadata-Version: 2.3
Name: spa-json-py
Version: 0.0.1
Summary: a python package to build static page apps running on json documents
License: MIT
Author: SVJ
Author-email: shubhvjain@gmail.com
Requires-Python: >=3.10,<4.0
Classifier: License :: OSI Approved :: MIT License
Classifier: Programming Language :: Python :: 3
Classifier: Programming Language :: Python :: 3.10
Classifier: Programming Language :: Python :: 3.11
Classifier: Programming Language :: Python :: 3.12
Classifier: Programming Language :: Python :: 3.13
